{
  "id": "17492",
  "title": "countryCode",
  "description": "The country from which the browser initiated the page load. For a list of country codes, see ISO 3166-1 alpha-2.",
  "eventTypes": [
    "PageView",
    "PageAction",
    "BrowserInteraction",
    "AjaxRequest",
    "BrowserTiming",
    "MobileSession",
    "PageViewTiming",
    "JavaScriptError"
  ],
  "relatedInfo": "<h2>Related Info</h2><p>For a list of country codes, see <a href=\"http://en.wikipedia.org/wiki/ISO_3166-1_alpha-2#Current_codes\" target=\"_blank\" title=\"Link opens in a new window.\">ISO 3166-1 alpha-2</a>.</p>\r\n\r\n<p>For more information about the Browser data and events, see <a href=\"https://docs.newrelic.com/docs/insights/insights-data-sources/default-data/browser-default-events-insights\">Browser default events for Insights</a>.</p>\r\n\r\n<p>For more information about Mobile data and events, see <a href=\"https://docs.newrelic.com/docs/insights/insights-data-sources/default-data/mobile-events\">Mobile events</a>.</p>\r\n\r\n<p></p>\r\n\r\n<p></p>\r\n"
}