{"expireTime":9007200872727671000,"key":"873ceb9b77b7b0bf94304b889d638847","val":{"name":"IMAGE_PROCESSING","inputPaths":["/Users/barb/Documents/GitHub/docs-website/src/content/docs/agents/php-agent/troubleshooting/images/doc_example_phpinfo_top_0.png"],"outputDir":"/Users/barb/Documents/GitHub/docs-website/public/static/103399fd906e33227636c585614fcebe","args":{"isLazy":false,"operations":[{"outputPath":"5a46d/doc_example_phpinfo_top_0.png","args":{"width":300,"toFormat":"png"}},{"outputPath":"0a47e/doc_example_phpinfo_top_0.png","args":{"width":600,"toFormat":"png"}},{"outputPath":"40040/doc_example_phpinfo_top_0.png","args":{"width":616,"toFormat":"png"}}],"pluginOptions":{"base64Width":20,"forceBase64Format":"","useMozJpeg":false,"stripMetadata":true,"lazyImageGeneration":true,"defaultQuality":50,"failOnError":true,"plugins":[]}}}}