{"expireTime":9007200872727552000,"key":"153c9b2e98c52d12d6e693f416a02aa2","val":{"name":"IMAGE_PROCESSING","inputPaths":["/Users/barb/Documents/GitHub/docs-website/src/content/docs/synthetics/synthetic-monitoring/using-monitors/images/transaction-trace.png"],"outputDir":"/Users/barb/Documents/GitHub/docs-website/public/static/07b8ae7d874fb474502a598936503964","args":{"isLazy":false,"operations":[{"outputPath":"5a46d/transaction-trace.png","args":{"width":300,"toFormat":"png"}},{"outputPath":"0a47e/transaction-trace.png","args":{"width":600,"toFormat":"png"}},{"outputPath":"c1b63/transaction-trace.png","args":{"width":1200,"toFormat":"png"}},{"outputPath":"ad00e/transaction-trace.png","args":{"width":1366,"toFormat":"png"}}],"pluginOptions":{"base64Width":20,"forceBase64Format":"","useMozJpeg":false,"stripMetadata":true,"lazyImageGeneration":true,"defaultQuality":50,"failOnError":true,"plugins":[]}}}}